LICENSE
README.md
RELEASES.md
SECURITY.md
demo/demo_mccache.py
mccache/__about__.py
mccache/__init__.py
mccache/__main__.py
pycache/__about__.py
pycache/__init__.py
mccache-0.4.12.dist-info/METADATA
mccache-0.4.12.dist-info/WHEEL
mccache-0.4.12.dist-info/licenses/LICENSE
mccache-0.4.12.dist-info/RECORD
