Metadata-Version: 2.4
Name: McCache
Version: 0.4.12
Summary: McCache is a, write through cluster aware, local in-memory caching library.
Project-URL: Homepage, https://github.com/McCache/McCache-for-Python
Project-URL: Source, https://github.com/McCache/McCache-for-Python
Project-URL: Issues, https://github.com/McCache/McCache-for-Python/issues
Author-email: Edward Lau <elau1004@netscape.net>
Maintainer-email: Edward Lau <elau1004@netscape.net>
License-Expression: MIT
License-File: LICENSE
Keywords: cache,cluster,distributed,eventual,local,mccache,multicast,optimistic,performance,scale-out,scale-up,udp
Classifier: Development Status :: 4 - Beta
Classifier: Intended Audience :: Developers
Classifier: License :: OSI Approved :: MIT License
Classifier: Operating System :: OS Independent
Classifier: Programming Language :: Python :: 3
Classifier: Programming Language :: Python :: 3.10
Classifier: Programming Language :: Python :: 3.11
Classifier: Programming Language :: Python :: 3.12
Classifier: Programming Language :: Python :: 3.13
Classifier: Programming Language :: Python :: Implementation :: CPython
Classifier: Topic :: Software Development :: Libraries :: Python Modules
Requires-Python: >=3.10
Requires-Dist: psutil>=5.9.5
